notifier.py
demo_notification_6100-0.1.0.dist-info/LICENSE
demo_notification_6100-0.1.0.dist-info/METADATA
demo_notification_6100-0.1.0.dist-info/WHEEL
demo_notification_6100-0.1.0.dist-info/top_level.txt
demo_notification_6100-0.1.0.dist-info/RECORD
