Metadata-Version: 2.2
Name: demo_notification_6100
Version: 0.1.0
Summary: Notification System
Requires-Python: >=3.6
License-File: LICENSE
